pytest_missing_fixtures.py
pytest_missing_fixtures-0.1.0.dist-info/LICENSE
pytest_missing_fixtures-0.1.0.dist-info/METADATA
pytest_missing_fixtures-0.1.0.dist-info/WHEEL
pytest_missing_fixtures-0.1.0.dist-info/entry_points.txt
pytest_missing_fixtures-0.1.0.dist-info/top_level.txt
pytest_missing_fixtures-0.1.0.dist-info/RECORD
